LICENSE.txt
MANIFEST.in
README.md
setup.cfg
setup.py
jani_text_cleaning/NLPCleaning.py
jani_text_cleaning/__init__.py
jani_text_cleaning.egg-info/PKG-INFO
jani_text_cleaning.egg-info/SOURCES.txt
jani_text_cleaning.egg-info/dependency_links.txt
jani_text_cleaning.egg-info/requires.txt
jani_text_cleaning.egg-info/top_level.txt
jani_text_cleaning/cleaning/cases.py
jani_text_cleaning/cleaning/htmls.py
jani_text_cleaning/cleaning/hyperlinks.py
jani_text_cleaning/cleaning/method.py
jani_text_cleaning/cleaning/punctuations.py
jani_text_cleaning/cleaning/specials.py
jani_text_cleaning/cleaning/stopwords.py
jani_text_cleaning/cleaning/tokenize.py